thumbor-7.7.7.dist-info/RECORD
thumbor-7.7.7.dist-info/WHEEL
thumbor-7.7.7.dist-info/entry_points.txt
thumbor-7.7.7.dist-info/top_level.txt
thumbor-7.7.7.dist-info/METADATA
thumbor-7.7.7.dist-info/licenses/LICENSE
thumbor/console.py
thumbor/server.py
thumbor/config.py
thumbor/importer.py
thumbor/threadpool.py
thumbor/thumbor.conf
thumbor/__init__.py
thumbor/point.py
thumbor/url.py
thumbor/url_composer.py
thumbor/signal_handler.py
thumbor/context.py
thumbor/utils.py
thumbor/transformer.py
thumbor/app.py
thumbor/testing.py
thumbor/doctor.py
thumbor/compatibility/compat.py
thumbor/compatibility/result_storage.py
thumbor/compatibility/__init__.py
thumbor/compatibility/loader.py
thumbor/compatibility/storage.py
thumbor/filters/saturation.py
thumbor/filters/focal.py
thumbor/filters/convolution.py
thumbor/filters/stretch.py
thumbor/filters/background_color.py
thumbor/filters/watermark.py
thumbor/filters/fill.py
thumbor/filters/round_corner.py
thumbor/filters/grayscale.py
thumbor/filters/max_bytes.py
thumbor/filters/haarcascade_eye.xml
thumbor/filters/upscale.py
thumbor/filters/__init__.py
thumbor/filters/format.py
thumbor/filters/redeye.py
thumbor/filters/sharpen.py
thumbor/filters/equalize.py
thumbor/filters/curve.py
thumbor/filters/proportion.py
thumbor/filters/max_age.py
thumbor/filters/blur.py
thumbor/filters/rgb.py
thumbor/filters/strip_icc.py
thumbor/filters/noise.py
thumbor/filters/frame.py
thumbor/filters/colorize.py
thumbor/filters/brightness.py
thumbor/filters/extract_focal.py
thumbor/filters/strip_exif.py
thumbor/filters/rotate.py
thumbor/filters/quality.py
thumbor/filters/contrast.py
thumbor/filters/autojpg.py
thumbor/filters/no_upscale.py
thumbor/metrics/logger_metrics.py
thumbor/metrics/__init__.py
thumbor/metrics/statsd_metrics.py
thumbor/storages/mixed_storage.py
thumbor/storages/no_storage.py
thumbor/storages/__init__.py
thumbor/storages/file_storage.py
thumbor/url_signers/__init__.py
thumbor/error_handlers/__init__.py
thumbor/error_handlers/file.py
thumbor/error_handlers/sentry.py
thumbor/ext/__init__.py
thumbor/ext/filters/_contrast.abi3.so
thumbor/ext/filters/_nine_patch.abi3.so
