Metadata-Version: 2.4
Name: thumbor
Version: 7.7.7
Summary: thumbor is an open-source photo thumbnail service by globo.com
Home-page: https://github.com/thumbor/thumbor/wiki
Author: globo.com
Author-email: thumbor@googlegroups.com
License: MIT
Keywords: imaging face detection feature thumbnail imagemagick pil opencv
Classifier: Development Status :: 4 - Beta
Classifier: Intended Audience :: Developers
Classifier: License :: OSI Approved :: MIT License
Classifier: Natural Language :: English
Classifier: Operating System :: MacOS
Classifier: Operating System :: POSIX :: Linux
Classifier: Programming Language :: Python :: 3
Classifier: Programming Language :: Python :: 3.9
Classifier: Programming Language :: Python :: 3.10
Classifier: Programming Language :: Python :: 3.11
Classifier: Programming Language :: Python :: 3.12
Classifier: Programming Language :: Python :: 3.13
Classifier: Programming Language :: Python :: 3 :: Only
Classifier: Topic :: Internet :: WWW/HTTP :: Dynamic Content
Classifier: Topic :: Multimedia :: Graphics :: Presentation
Requires-Python: >=3.9
License-File: LICENSE
Requires-Dist: colorama==0.*,>=0.4.6
Requires-Dist: derpconf==0.*,>=0.8.4
Requires-Dist: JpegIPTC==1.*,>=1.5
Requires-Dist: libthumbor==2.*,>=2.0.2
Requires-Dist: piexif==1.*,>=1.1.3
Requires-Dist: Pillow<11.0.0,>=10.4.0
Requires-Dist: pytz==2023.*,>=2023.3.post1
Requires-Dist: setuptools==75.*,>=75.2.0
Requires-Dist: statsd==4.*,>=4.0.1
Requires-Dist: thumbor-plugins-gifv==0.*,>=0.1.5
Requires-Dist: tornado==6.*,>=6.4
Requires-Dist: webcolors==1.*,>=1.13.0
Provides-Extra: all
Requires-Dist: opencv-python-headless==4.*,>=4.9.0.80; extra == "all"
Requires-Dist: numpy==1.*,>=1.26.3; extra == "all"
Requires-Dist: cairosvg==2.*,>=2.7.1; extra == "all"
Requires-Dist: pycurl==7.*,>=7.45.2; extra == "all"
Requires-Dist: pillow-avif-plugin==1.*,>=1.4.1; extra == "all"
Requires-Dist: pillow-heif==0.*,>=0.22.0; extra == "all"
Provides-Extra: opencv
Requires-Dist: opencv-python-headless==4.*,>=4.9.0.80; extra == "opencv"
Requires-Dist: numpy==1.*,>=1.26.3; extra == "opencv"
Provides-Extra: tests
Requires-Dist: opencv-python-headless==4.*,>=4.9.0.80; extra == "tests"
Requires-Dist: numpy==1.*,>=1.26.3; extra == "tests"
Requires-Dist: cairosvg==2.*,>=2.7.1; extra == "tests"
Requires-Dist: pycurl==7.*,>=7.45.2; extra == "tests"
Requires-Dist: pillow-avif-plugin==1.*,>=1.4.1; extra == "tests"
Requires-Dist: pillow-heif==0.*,>=0.22.0; extra == "tests"
Requires-Dist: coverage==7.*,>=7.4.0; extra == "tests"
Requires-Dist: flake8==7.*,>=7.0.0; extra == "tests"
Requires-Dist: isort==5.*,>=5.13.2; extra == "tests"
Requires-Dist: pre-commit==3.*,>=3.6.0; extra == "tests"
Requires-Dist: preggy==1.*,>=1.4.4; extra == "tests"
Requires-Dist: pylint==3.*,>=3.0.3; extra == "tests"
Requires-Dist: pyssim==0.*,>=0.7; extra == "tests"
Requires-Dist: pytest==7.*,>=7.4.4; extra == "tests"
Requires-Dist: pytest-asyncio==0.*,>=0.23.3; extra == "tests"
Requires-Dist: pytest-cov==4.*,>=4.1.0; extra == "tests"
Requires-Dist: pytest-tldr==0.*,>=0.2.5; extra == "tests"
Requires-Dist: pytest-xdist==3.*,>=3.5.0; extra == "tests"
Requires-Dist: redis==5.*,>=5.0.1; extra == "tests"
Requires-Dist: remotecv==5.*,>=5.1.8; extra == "tests"
Requires-Dist: sentry-sdk==1.*,>=1.39.1; extra == "tests"
Requires-Dist: yanc==0.*,>=0.3.3; extra == "tests"
Dynamic: author
Dynamic: author-email
Dynamic: classifier
Dynamic: description
Dynamic: description-content-type
Dynamic: home-page
Dynamic: keywords
Dynamic: license
Dynamic: license-file
Dynamic: provides-extra
Dynamic: requires-dist
Dynamic: requires-python
Dynamic: summary
